Workbook

Sheet Start Here
A1: Yorosum accounting: how this file works
A2: Blue text = you type it. Black = calculated. Yellow = please replace with your real number.
A4: 1. Production | B4: Each time CNS Pharm makes a batch, add the payments and the number of units. The file works out the cost per unit for that batch.
A6: 2. Lots | B6: Each time you send cartons somewhere, add one row: which batch, how many cartons, the freight rate. The file works out the landed cost per unit for that lot. Stock that stays in Korea is its own lot: leave Cartons empty and it gets whatever is left of the batch.
A8: 3. Pricing | B8: Pick a lot for each sales channel and set the margin you want. The file shows the price to charge. Or type a price and see the margin it gives.
A10: 4. Sales | B10: Add each sale: date, lot, channel, units, price. Profit uses the real cost of that lot. Units left in each lot update on the Lots tab.
A12: 5. Expenses | B12: Add running costs (AI tools, marketing, registration...).
A14: 6. Summary | B14: Totals: money spent, stock left in Korea and Uzbekistan, sales, profit by month.
A17: Why lots? | B17: Each batch can cost a different amount to make, and each shipment can cost a different amount to fly. Keeping them as separate lots means every price and profit uses the real cost of the stock you are selling.

Sheet Production
A1: Production batches
A2: Left: every payment to the factory. Right: one row per batch with its units and cost per unit.
A4: Date | B4: Batch | C4: Amount paid (KRW) | D4: What it was for | F4: Batch | G4: Units made | H4: Total paid (KRW) | I4: Cost per unit (KRW) | J4: Cost per unit (USD)
A5: 46254 | B5: B1 | C5: 9000000 | D5: Production payment | F5: B1 | G5: 2793 | H5: =SUMIFS($C:$C,$B:$B,F5) | I5: =IF(N(G5)=0,"",H5/G5) | J5: =IF(I5="","",I5/Pricing!$B$5)
A6: 46307 | B6: B1 | C6: 10000000 | D6: Production payment | F6: B2 | H6: =SUMIFS($C:$C,$B:$B,F6) | I6: =IF(N(G6)=0,"",H6/G6) | J6: =IF(I6="","",I6/Pricing!$B$5)
A7: 46308 | B7: B1 | C7: 450640 | D7: Not labelled in the original sheet | F7: B3 | H7: =SUMIFS($C:$C,$B:$B,F7) | I7: =IF(N(G7)=0,"",H7/G7) | J7: =IF(I7="","",I7/Pricing!$B$5)
A8: 46309 | B8: B1 | C8: 564696 | D8: Not labelled in the original sheet | F8: B4 | H8: =SUMIFS($C:$C,$B:$B,F8) | I8: =IF(N(G8)=0,"",H8/G8) | J8: =IF(I8="","",I8/Pricing!$B$5)
F10: Batch B1 payments and units are from your original sheet.

Sheet Lots
A1: Lots (each shipment, plus stock left in Korea)
A2: One row per shipment. For stock that stays in Korea, leave Cartons empty: it gets whatever units of the batch were not shipped.
A4: Lot | B4: Date | C4: Batch | D4: Location | E4: Cartons | F4: Units per carton | G4: Units | H4: Carton weight (kg) | I4: Freight rate (USD/kg) | J4: Freight invoice (USD, optional) | K4: Freight (USD) | L4: Customs and other import costs (KRW) | M4: Factory cost per unit (KRW) | N4: Freight per unit (KRW) | O4: Other costs per unit (KRW) | P4: Landed cost per unit (KRW) | Q4: Units sold | R4: Units left
A5: B1-UZ1 | B5: 46310 | C5: B1 | D5: Uzbekistan | E5: 33 | F5: 42 | G5: =IF($A5="","",IF($E5="",IFERROR(VLOOKUP($C5,Production!$F$5:$G$30,2,FALSE),0)-SUMPRODUCT(($C$5:$C$24=$C5)*N(+$E$5:$E$24)*N(+$F$5:$F$24)),$E5*$F5)) | H5: 6.5 | I5: 9 | K5: =IF($A5="","",IF($J5<>"",$J5,N($E5)*N($H5)*N($I5))) | L5: 0 | M5: =IF($A5="","",IFERROR(VLOOKUP($C5,Production!$F$5:$I$30,4,FALSE),0)) | N5: =IF(N($G5)=0,"",$K5*Pricing!$B$5/$G5) | O5: =IF(N($G5)=0,"",N($L5)/$G5) | P5: =IF($A5="","",$M5+N($N5)+N($O5)) | Q5: =IF($A5="","",SUMIFS(Sales!$D:$D,Sales!$B:$B,$A5)) | R5: =IF($A5="","",$G5-$Q5)
A6: B1-KR | C6: B1 | D6: Korea | G6: =IF($A6="","",IF($E6="",IFERROR(VLOOKUP($C6,Production!$F$5:$G$30,2,FALSE),0)-SUMPRODUCT(($C$5:$C$24=$C6)*N(+$E$5:$E$24)*N(+$F$5:$F$24)),$E6*$F6)) | K6: =IF($A6="","",IF($J6<>"",$J6,N($E6)*N($H6)*N($I6))) | M6: =IF($A6="","",IFERROR(VLOOKUP($C6,Production!$F$5:$I$30,4,FALSE),0)) | N6: =IF(N($G6)=0,"",$K6*Pricing!$B$5/$G6) | O6: =IF(N($G6)=0,"",N($L6)/$G6) | P6: =IF($A6="","",$M6+N($N6)+N($O6)) | Q6: =IF($A6="","",SUMIFS(Sales!$D:$D,Sales!$B:$B,$A6)) | R6: =IF($A6="","",$G6-$Q6)
G7: =IF($A7="","",IF($E7="",IFERROR(VLOOKUP($C7,Production!$F$5:$G$30,2,FALSE),0)-SUMPRODUCT(($C$5:$C$24=$C7)*N(+$E$5:$E$24)*N(+$F$5:$F$24)),$E7*$F7)) | K7: =IF($A7="","",IF($J7<>"",$J7,N($E7)*N($H7)*N($I7))) | M7: =IF($A7="","",IFERROR(VLOOKUP($C7,Production!$F$5:$I$30,4,FALSE),0)) | N7: =IF(N($G7)=0,"",$K7*Pricing!$B$5/$G7) | O7: =IF(N($G7)=0,"",N($L7)/$G7) | P7: =IF($A7="","",$M7+N($N7)+N($O7)) | Q7: =IF($A7="","",SUMIFS(Sales!$D:$D,Sales!$B:$B,$A7)) | R7: =IF($A7="","",$G7-$Q7)
G8: =IF($A8="","",IF($E8="",IFERROR(VLOOKUP($C8,Production!$F$5:$G$30,2,FALSE),0)-SUMPRODUCT(($C$5:$C$24=$C8)*N(+$E$5:$E$24)*N(+$F$5:$F$24)),$E8*$F8)) | K8: =IF($A8="","",IF($J8<>"",$J8,N($E8)*N($H8)*N($I8))) | M8: =IF($A8="","",IFERROR(VLOOKUP($C8,Production!$F$5:$I$30,4,FALSE),0)) | N8: =IF(N($G8)=0,"",$K8*Pricing!$B$5/$G8) | O8: =IF(N($G8)=0,"",N($L8)/$G8) | P8: =IF($A8="","",$M8+N($N8)+N($O8)) | Q8: =IF($A8="","",SUMIFS(Sales!$D:$D,Sales!$B:$B,$A8)) | R8: =IF($A8="","",$G8-$Q8)
G9: =IF($A9="","",IF($E9="",IFERROR(VLOOKUP($C9,Production!$F$5:$G$30,2,FALSE),0)-SUMPRODUCT(($C$5:$C$24=$C9)*N(+$E$5:$E$24)*N(+$F$5:$F$24)),$E9*$F9)) | K9: =IF($A9="","",IF($J9<>"",$J9,N($E9)*N($H9)*N($I9))) | M9: =IF($A9="","",IFERROR(VLOOKUP($C9,Production!$F$5:$I$30,4,FALSE),0)) | N9: =IF(N($G9)=0,"",$K9*Pricing!$B$5/$G9) | O9: =IF(N($G9)=0,"",N($L9)/$G9) | P9: =IF($A9="","",$M9+N($N9)+N($O9)) | Q9: =IF($A9="","",SUMIFS(Sales!$D:$D,Sales!$B:$B,$A9)) | R9: =IF($A9="","",$G9-$Q9)
G10: =IF($A10="","",IF($E10="",IFERROR(VLOOKUP($C10,Production!$F$5:$G$30,2,FALSE),0)-SUMPRODUCT(($C$5:$C$24=$C10)*N(+$E$5:$E$24)*N(+$F$5:$F$24)),$E10*$F10)) | K10: =IF($A10="","",IF($J10<>"",$J10,N($E10)*N($H10)*N($I10))) | M10: =IF($A10="","",IFERROR(VLOOKUP($C10,Production!$F$5:$I$30,4,FALSE),0)) | N10: =IF(N($G10)=0,"",$K10*Pricing!$B$5/$G10) | O10: =IF(N($G10)=0,"",N($L10)/$G10) | P10: =IF($A10="","",$M10+N($N10)+N($O10)) | Q10: =IF($A10="","",SUMIFS(Sales!$D:$D,Sales!$B:$B,$A10)) | R10: =IF($A10="","",$G10-$Q10)
G11: =IF($A11="","",IF($E11="",IFERROR(VLOOKUP($C11,Production!$F$5:$G$30,2,FALSE),0)-SUMPRODUCT(($C$5:$C$24=$C11)*N(+$E$5:$E$24)*N(+$F$5:$F$24)),$E11*$F11)) | K11: =IF($A11="","",IF($J11<>"",$J11,N($E11)*N($H11)*N($I11))) | M11: =IF($A11="","",IFERROR(VLOOKUP($C11,Production!$F$5:$I$30,4,FALSE),0)) | N11: =IF(N($G11)=0,"",$K11*Pricing!$B$5/$G11) | O11: =IF(N($G11)=0,"",N($L11)/$G11) | P11: =IF($A11="","",$M11+N($N11)+N($O11)) | Q11: =IF($A11="","",SUMIFS(Sales!$D:$D,Sales!$B:$B,$A11)) | R11: =IF($A11="","",$G11-$Q11)
G12: =IF($A12="","",IF($E12="",IFERROR(VLOOKUP($C12,Production!$F$5:$G$30,2,FALSE),0)-SUMPRODUCT(($C$5:$C$24=$C12)*N(+$E$5:$E$24)*N(+$F$5:$F$24)),$E12*$F12)) | K12: =IF($A12="","",IF($J12<>"",$J12,N($E12)*N($H12)*N($I12))) | M12: =IF($A12="","",IFERROR(VLOOKUP($C12,Production!$F$5:$I$30,4,FALSE),0)) | N12: =IF(N($G12)=0,"",$K12*Pricing!$B$5/$G12) | O12: =IF(N($G12)=0,"",N($L12)/$G12) | P12: =IF($A12="","",$M12+N($N12)+N($O12)) | Q12: =IF($A12="","",SUMIFS(Sales!$D:$D,Sales!$B:$B,$A12)) | R12: =IF($A12="","",$G12-$Q12)
G13: =IF($A13="","",IF($E13="",IFERROR(VLOOKUP($C13,Production!$F$5:$G$30,2,FALSE),0)-SUMPRODUCT(($C$5:$C$24=$C13)*N(+$E$5:$E$24)*N(+$F$5:$F$24)),$E13*$F13)) | K13: =IF($A13="","",IF($J13<>"",$J13,N($E13)*N($H13)*N($I13))) | M13: =IF($A13="","",IFERROR(VLOOKUP($C13,Production!$F$5:$I$30,4,FALSE),0)) | N13: =IF(N($G13)=0,"",$K13*Pricing!$B$5/$G13) | O13: =IF(N($G13)=0,"",N($L13)/$G13) | P13: =IF($A13="","",$M13+N($N13)+N($O13)) | Q13: =IF($A13="","",SUMIFS(Sales!$D:$D,Sales!$B:$B,$A13)) | R13: =IF($A13="","",$G13-$Q13)
G14: =IF($A14="","",IF($E14="",IFERROR(VLOOKUP($C14,Production!$F$5:$G$30,2,FALSE),0)-SUMPRODUCT(($C$5:$C$24=$C14)*N(+$E$5:$E$24)*N(+$F$5:$F$24)),$E14*$F14)) | K14: =IF($A14="","",IF($J14<>"",$J14,N($E14)*N($H14)*N($I14))) | M14: =IF($A14="","",IFERROR(VLOOKUP($C14,Production!$F$5:$I$30,4,FALSE),0)) | N14: =IF(N($G14)=0,"",$K14*Pricing!$B$5/$G14) | O14: =IF(N($G14)=0,"",N($L14)/$G14) | P14: =IF($A14="","",$M14+N($N14)+N($O14)) | Q14: =IF($A14="","",SUMIFS(Sales!$D:$D,Sales!$B:$B,$A14)) | R14: =IF($A14="","",$G14-$Q14)
G15: =IF($A15="","",IF($E15="",IFERROR(VLOOKUP($C15,Production!$F$5:$G$30,2,FALSE),0)-SUMPRODUCT(($C$5:$C$24=$C15)*N(+$E$5:$E$24)*N(+$F$5:$F$24)),$E15*$F15)) | K15: =IF($A15="","",IF($J15<>"",$J15,N($E15)*N($H15)*N($I15))) | M15: =IF($A15="","",IFERROR(VLOOKUP($C15,Production!$F$5:$I$30,4,FALSE),0)) | N15: =IF(N($G15)=0,"",$K15*Pricing!$B$5/$G15) | O15: =IF(N($G15)=0,"",N($L15)/$G15) | P15: =IF($A15="","",$M15+N($N15)+N($O15)) | Q15: =IF($A15="","",SUMIFS(Sales!$D:$D,Sales!$B:$B,$A15)) | R15: =IF($A15="","",$G15-$Q15)
G16: =IF($A16="","",IF($E16="",IFERROR(VLOOKUP($C16,Production!$F$5:$G$30,2,FALSE),0)-SUMPRODUCT(($C$5:$C$24=$C16)*N(+$E$5:$E$24)*N(+$F$5:$F$24)),$E16*$F16)) | K16: =IF($A16="","",IF($J16<>"",$J16,N($E16)*N($H16)*N($I16))) | M16: =IF($A16="","",IFERROR(VLOOKUP($C16,Production!$F$5:$I$30,4,FALSE),0)) | N16: =IF(N($G16)=0,"",$K16*Pricing!$B$5/$G16) | O16: =IF(N($G16)=0,"",N($L16)/$G16) | P16: =IF($A16="","",$M16+N($N16)+N($O16)) | Q16: =IF($A16="","",SUMIFS(Sales!$D:$D,Sales!$B:$B,$A16)) | R16: =IF($A16="","",$G16-$Q16)
G17: =IF($A17="","",IF($E17="",IFERROR(VLOOKUP($C17,Production!$F$5:$G$30,2,FALSE),0)-SUMPRODUCT(($C$5:$C$24=$C17)*N(+$E$5:$E$24)*N(+$F$5:$F$24)),$E17*$F17)) | K17: =IF($A17="","",IF($J17<>"",$J17,N($E17)*N($H17)*N($I17))) | M17: =IF($A17="","",IFERROR(VLOOKUP($C17,Production!$F$5:$I$30,4,FALSE),0)) | N17: =IF(N($G17)=0,"",$K17*Pricing!$B$5/$G17) | O17: =IF(N($G17)=0,"",N($L17)/$G17) | P17: =IF($A17="","",$M17+N($N17)+N($O17)) | Q17: =IF($A17="","",SUMIFS(Sales!$D:$D,Sales!$B:$B,$A17)) | R17: =IF($A17="","",$G17-$Q17)
G18: =IF($A18="","",IF($E18="",IFERROR(VLOOKUP($C18,Production!$F$5:$G$30,2,FALSE),0)-SUMPRODUCT(($C$5:$C$24=$C18)*N(+$E$5:$E$24)*N(+$F$5:$F$24)),$E18*$F18)) | K18: =IF($A18="","",IF($J18<>"",$J18,N($E18)*N($H18)*N($I18))) | M18: =IF($A18="","",IFERROR(VLOOKUP($C18,Production!$F$5:$I$30,4,FALSE),0)) | N18: =IF(N($G18)=0,"",$K18*Pricing!$B$5/$G18) | O18: =IF(N($G18)=0,"",N($L18)/$G18) | P18: =IF($A18="","",$M18+N($N18)+N($O18)) | Q18: =IF($A18="","",SUMIFS(Sales!$D:$D,Sales!$B:$B,$A18)) | R18: =IF($A18="","",$G18-$Q18)
... G24: =IF($A24="","",IF($E24="",IFERROR(VLOOKUP($C24,Production!$F$5:$G$30,2,FALSE),0)-SUMPRODUCT(($C$5:$C$24=$C24)*N(+$E$5:$E$24)*N(+$F$5:$F$24)),$E24*$F24)) | K24: =IF($A24="","",IF($J24<>"",$J24,N($E24)*N($H24)*N($I24))) | M24: =IF($A24="","",IFERROR(VLOOKUP($C24,Production!$F$5:$I$30,4,FALSE),0)) | N24: =IF(N($G24)=0,"",$K24*Pricing!$B$5/$G24) | O24: =IF(N($G24)=0,"",N($L24)/$G24) | P24: =IF($A24="","",$M24+N($N24)+N($O24)) | Q24: =IF($A24="","",SUMIFS(Sales!$D:$D,Sales!$B:$B,$A24)) | R24: =IF($A24="","",$G24-$Q24)
A26: Rows 5 to 24 are ready to use. Freight = cartons x carton weight x rate, unless you type the real freight invoice amount.

Sheet Pricing
A1: Pricing
A2: Pick a lot for each channel and set the margin you want, or type your own price. Green rows are the answers.
A4: Exchange rates
A5: KRW per 1 USD | B5: 1327 | C5: Your rates from the original sheet. Update them when they change.
A6: UZS per 1 USD | B6: 12040
A7: KRW per 1 UZS | B7: =B5/B6
B9: Uzbekistan B2B | C9: Uzbekistan B2C | D9: Korea B2B | E9: Korea B2C
A10: Your choices
A11: Lot you are selling from | B11: B1-UZ1 | C11: B1-UZ1 | D11: B1-KR | E11: B1-KR
A12: Currency you sell in | B12: UZS | C12: UZS | D12: KRW | E12: KRW
A13: VAT | B13: 0.12 | C13: 0.12 | D13: 0.1 | E13: 0.1
A14: Marketplace and payment fees (% of price with VAT) | B14: 0 | C14: 0 | D14: 0 | E14: 0
A15: Delivery and packaging per unit (KRW) | B15: 0 | C15: 0 | D15: 0 | E15: 0
A16: Margin you want | B16: 0.35 | C16: 0.6 | D16: 0.3 | E16: 0.5
A17: Or: your own price with VAT (in the selling currency)
A19: Results
A20: KRW per 1 unit of selling currency (helper) | B20: =IF(B12="UZS",$B$7,IF(B12="USD",$B$5,1)) | C20: =IF(C12="UZS",$B$7,IF(C12="USD",$B$5,1)) | D20: =IF(D12="UZS",$B$7,IF(D12="USD",$B$5,1)) | E20: =IF(E12="UZS",$B$7,IF(E12="USD",$B$5,1))
A21: Landed cost per unit (KRW) | B21: =IFERROR(VLOOKUP(B11,Lots!$A$5:$P$24,16,FALSE),NA()) | C21: =IFERROR(VLOOKUP(C11,Lots!$A$5:$P$24,16,FALSE),NA()) | D21: =IFERROR(VLOOKUP(D11,Lots!$A$5:$P$24,16,FALSE),NA()) | E21: =IFERROR(VLOOKUP(E11,Lots!$A$5:$P$24,16,FALSE),NA())
A22: Price before VAT (KRW) | B22: =IF(B17<>"",B17*B20/(1+B13),IF(1-B14*(1+B13)-B16<=0,NA(),(B21+B15)/(1-B14*(1+B13)-B16))) | C22: =IF(C17<>"",C17*C20/(1+C13),IF(1-C14*(1+C13)-C16<=0,NA(),(C21+C15)/(1-C14*(1+C13)-C16))) | D22: =IF(D17<>"",D17*D20/(1+D13),IF(1-D14*(1+D13)-D16<=0,NA(),(D21+D15)/(1-D14*(1+D13)-D16))) | E22: =IF(E17<>"",E17*E20/(1+E13),IF(1-E14*(1+E13)-E16<=0,NA(),(E21+E15)/(1-E14*(1+E13)-E16)))
A23: Price with VAT (KRW) | B23: =B22*(1+B13) | C23: =C22*(1+C13) | D23: =D22*(1+D13) | E23: =E22*(1+E13)
A24: PRICE TO CHARGE, with VAT (selling currency) | B24: =B23/B20 | C24: =C23/C20 | D24: =D23/D20 | E24: =E23/E20
A25: Price with VAT (USD) | B25: =B23/$B$5 | C25: =C23/$B$5 | D25: =D23/$B$5 | E25: =E23/$B$5
A26: Fees per unit (KRW) | B26: =B23*B14 | C26: =C23*C14 | D26: =D23*D14 | E26: =E23*E14
A27: PROFIT PER UNIT (KRW) | B27: =B22-B26-B15-B21 | C27: =C22-C26-C15-C21 | D27: =D22-D26-D15-D21 | E27: =E22-E26-E15-E21
A28: Profit per unit (selling currency) | B28: =B27/B20 | C28: =C27/C20 | D28: =D27/D20 | E28: =E27/E20
A29: MARGIN (profit / price before VAT) | B29: =IF(B22=0,0,B27/B22) | C29: =IF(C22=0,0,C27/C22) | D29: =IF(D22=0,0,D27/D22) | E29: =IF(E22=0,0,E27/E22)
A30: Units left in this lot | B30: =IFERROR(VLOOKUP(B11,Lots!$A$5:$R$24,18,FALSE),0) | C30: =IFERROR(VLOOKUP(C11,Lots!$A$5:$R$24,18,FALSE),0) | D30: =IFERROR(VLOOKUP(D11,Lots!$A$5:$R$24,18,FALSE),0) | E30: =IFERROR(VLOOKUP(E11,Lots!$A$5:$R$24,18,FALSE),0)
A31: Profit if all units left sell at this price (KRW) | B31: =B27*B30 | C31: =C27*C30 | D31: =D27*D30 | E31: =E27*E30

Sheet Sales
A1: Sales
A2: Type the blue columns. Profit uses the landed cost of the lot you sold from.
A4: Date | B4: Lot | C4: Channel | D4: Units | E4: Price per unit with VAT | F4: Currency | G4: Fees (KRW, optional) | H4: KRW per unit of currency | I4: VAT | J4: Revenue with VAT (KRW) | K4: Revenue before VAT (KRW) | L4: Cost of goods (KRW) | M4: Profit (KRW) | N4: Margin | O4: Month
H5: =IF($F5="","",IF($F5="UZS",Pricing!$B$7,IF($F5="USD",Pricing!$B$5,1))) | I5: =IF($C5="","",INDEX(Pricing!$B$13:$E$13,MATCH($C5,Pricing!$B$9:$E$9,0))) | J5: =IF($H5="","",$D5*$E5*$H5) | K5: =IF(OR($J5="",$I5=""),"",$J5/(1+$I5)) | L5: =IF($B5="","",$D5*IFERROR(VLOOKUP($B5,Lots!$A$5:$P$24,16,FALSE),0)) | M5: =IF($K5="","",$K5-N($G5)-$L5) | N5: =IF(N($K5)=0,"",$M5/$K5) | O5: =IF($A5="","",TEXT($A5,"yyyy-mm"))
H6: =IF($F6="","",IF($F6="UZS",Pricing!$B$7,IF($F6="USD",Pricing!$B$5,1))) | I6: =IF($C6="","",INDEX(Pricing!$B$13:$E$13,MATCH($C6,Pricing!$B$9:$E$9,0))) | J6: =IF($H6="","",$D6*$E6*$H6) | K6: =IF(OR($J6="",$I6=""),"",$J6/(1+$I6)) | L6: =IF($B6="","",$D6*IFERROR(VLOOKUP($B6,Lots!$A$5:$P$24,16,FALSE),0)) | M6: =IF($K6="","",$K6-N($G6)-$L6) | N6: =IF(N($K6)=0,"",$M6/$K6) | O6: =IF($A6="","",TEXT($A6,"yyyy-mm"))
H7: =IF($F7="","",IF($F7="UZS",Pricing!$B$7,IF($F7="USD",Pricing!$B$5,1))) | I7: =IF($C7="","",INDEX(Pricing!$B$13:$E$13,MATCH($C7,Pricing!$B$9:$E$9,0))) | J7: =IF($H7="","",$D7*$E7*$H7) | K7: =IF(OR($J7="",$I7=""),"",$J7/(1+$I7)) | L7: =IF($B7="","",$D7*IFERROR(VLOOKUP($B7,Lots!$A$5:$P$24,16,FALSE),0)) | M7: =IF($K7="","",$K7-N($G7)-$L7) | N7: =IF(N($K7)=0,"",$M7/$K7) | O7: =IF($A7="","",TEXT($A7,"yyyy-mm"))
H8: =IF($F8="","",IF($F8="UZS",Pricing!$B$7,IF($F8="USD",Pricing!$B$5,1))) | I8: =IF($C8="","",INDEX(Pricing!$B$13:$E$13,MATCH($C8,Pricing!$B$9:$E$9,0))) | J8: =IF($H8="","",$D8*$E8*$H8) | K8: =IF(OR($J8="",$I8=""),"",$J8/(1+$I8)) | L8: =IF($B8="","",$D8*IFERROR(VLOOKUP($B8,Lots!$A$5:$P$24,16,FALSE),0)) | M8: =IF($K8="","",$K8-N($G8)-$L8) | N8: =IF(N($K8)=0,"",$M8/$K8) | O8: =IF($A8="","",TEXT($A8,"yyyy-mm"))
H9: =IF($F9="","",IF($F9="UZS",Pricing!$B$7,IF($F9="USD",Pricing!$B$5,1))) | I9: =IF($C9="","",INDEX(Pricing!$B$13:$E$13,MATCH($C9,Pricing!$B$9:$E$9,0))) | J9: =IF($H9="","",$D9*$E9*$H9) | K9: =IF(OR($J9="",$I9=""),"",$J9/(1+$I9)) | L9: =IF($B9="","",$D9*IFERROR(VLOOKUP($B9,Lots!$A$5:$P$24,16,FALSE),0)) | M9: =IF($K9="","",$K9-N($G9)-$L9) | N9: =IF(N($K9)=0,"",$M9/$K9) | O9: =IF($A9="","",TEXT($A9,"yyyy-mm"))
H10: =IF($F10="","",IF($F10="UZS",Pricing!$B$7,IF($F10="USD",Pricing!$B$5,1))) | I10: =IF($C10="","",INDEX(Pricing!$B$13:$E$13,MATCH($C10,Pricing!$B$9:$E$9,0))) | J10: =IF($H10="","",$D10*$E10*$H10) | K10: =IF(OR($J10="",$I10=""),"",$J10/(1+$I10)) | L10: =IF($B10="","",$D10*IFERROR(VLOOKUP($B10,Lots!$A$5:$P$24,16,FALSE),0)) | M10: =IF($K10="","",$K10-N($G10)-$L10) | N10: =IF(N($K10)=0,"",$M10/$K10) | O10: =IF($A10="","",TEXT($A10,"yyyy-mm"))
H11: =IF($F11="","",IF($F11="UZS",Pricing!$B$7,IF($F11="USD",Pricing!$B$5,1))) | I11: =IF($C11="","",INDEX(Pricing!$B$13:$E$13,MATCH($C11,Pricing!$B$9:$E$9,0))) | J11: =IF($H11="","",$D11*$E11*$H11) | K11: =IF(OR($J11="",$I11=""),"",$J11/(1+$I11)) | L11: =IF($B11="","",$D11*IFERROR(VLOOKUP($B11,Lots!$A$5:$P$24,16,FALSE),0)) | M11: =IF($K11="","",$K11-N($G11)-$L11) | N11: =IF(N($K11)=0,"",$M11/$K11) | O11: =IF($A11="","",TEXT($A11,"yyyy-mm"))
H12: =IF($F12="","",IF($F12="UZS",Pricing!$B$7,IF($F12="USD",Pricing!$B$5,1))) | I12: =IF($C12="","",INDEX(Pricing!$B$13:$E$13,MATCH($C12,Pricing!$B$9:$E$9,0))) | J12: =IF($H12="","",$D12*$E12*$H12) | K12: =IF(OR($J12="",$I12=""),"",$J12/(1+$I12)) | L12: =IF($B12="","",$D12*IFERROR(VLOOKUP($B12,Lots!$A$5:$P$24,16,FALSE),0)) | M12: =IF($K12="","",$K12-N($G12)-$L12) | N12: =IF(N($K12)=0,"",$M12/$K12) | O12: =IF($A12="","",TEXT($A12,"yyyy-mm"))
H13: =IF($F13="","",IF($F13="UZS",Pricing!$B$7,IF($F13="USD",Pricing!$B$5,1))) | I13: =IF($C13="","",INDEX(Pricing!$B$13:$E$13,MATCH($C13,Pricing!$B$9:$E$9,0))) | J13: =IF($H13="","",$D13*$E13*$H13) | K13: =IF(OR($J13="",$I13=""),"",$J13/(1+$I13)) | L13: =IF($B13="","",$D13*IFERROR(VLOOKUP($B13,Lots!$A$5:$P$24,16,FALSE),0)) | M13: =IF($K13="","",$K13-N($G13)-$L13) | N13: =IF(N($K13)=0,"",$M13/$K13) | O13: =IF($A13="","",TEXT($A13,"yyyy-mm"))
H14: =IF($F14="","",IF($F14="UZS",Pricing!$B$7,IF($F14="USD",Pricing!$B$5,1))) | I14: =IF($C14="","",INDEX(Pricing!$B$13:$E$13,MATCH($C14,Pricing!$B$9:$E$9,0))) | J14: =IF($H14="","",$D14*$E14*$H14) | K14: =IF(OR($J14="",$I14=""),"",$J14/(1+$I14)) | L14: =IF($B14="","",$D14*IFERROR(VLOOKUP($B14,Lots!$A$5:$P$24,16,FALSE),0)) | M14: =IF($K14="","",$K14-N($G14)-$L14) | N14: =IF(N($K14)=0,"",$M14/$K14) | O14: =IF($A14="","",TEXT($A14,"yyyy-mm"))
H15: =IF($F15="","",IF($F15="UZS",Pricing!$B$7,IF($F15="USD",Pricing!$B$5,1))) | I15: =IF($C15="","",INDEX(Pricing!$B$13:$E$13,MATCH($C15,Pricing!$B$9:$E$9,0))) | J15: =IF($H15="","",$D15*$E15*$H15) | K15: =IF(OR($J15="",$I15=""),"",$J15/(1+$I15)) | L15: =IF($B15="","",$D15*IFERROR(VLOOKUP($B15,Lots!$A$5:$P$24,16,FALSE),0)) | M15: =IF($K15="","",$K15-N($G15)-$L15) | N15: =IF(N($K15)=0,"",$M15/$K15) | O15: =IF($A15="","",TEXT($A15,"yyyy-mm"))
H16: =IF($F16="","",IF($F16="UZS",Pricing!$B$7,IF($F16="USD",Pricing!$B$5,1))) | I16: =IF($C16="","",INDEX(Pricing!$B$13:$E$13,MATCH($C16,Pricing!$B$9:$E$9,0))) | J16: =IF($H16="","",$D16*$E16*$H16) | K16: =IF(OR($J16="",$I16=""),"",$J16/(1+$I16)) | L16: =IF($B16="","",$D16*IFERROR(VLOOKUP($B16,Lots!$A$5:$P$24,16,FALSE),0)) | M16: =IF($K16="","",$K16-N($G16)-$L16) | N16: =IF(N($K16)=0,"",$M16/$K16) | O16: =IF($A16="","",TEXT($A16,"yyyy-mm"))
... H44: =IF($F44="","",IF($F44="UZS",Pricing!$B$7,IF($F44="USD",Pricing!$B$5,1))) | I44: =IF($C44="","",INDEX(Pricing!$B$13:$E$13,MATCH($C44,Pricing!$B$9:$E$9,0))) | J44: =IF($H44="","",$D44*$E44*$H44) | K44: =IF(OR($J44="",$I44=""),"",$J44/(1+$I44)) | L44: =IF($B44="","",$D44*IFERROR(VLOOKUP($B44,Lots!$A$5:$P$24,16,FALSE),0)) | M44: =IF($K44="","",$K44-N($G44)-$L44) | N44: =IF(N($K44)=0,"",$M44/$K44) | O44: =IF($A44="","",TEXT($A44,"yyyy-mm"))
A46: Rows 5 to 44 are ready. For more, copy the last row down.

Sheet Expenses
A1: Running expenses
A2: First two rows are from your original sheet. Currency was not stated there, so KRW is assumed; the second date said 2027 and is set to 2026.
A4: Date | B4: Category | C4: Description | D4: Amount | E4: Currency | F4: Amount (KRW) | G4: Month
A5: 46230 | B5: AI tools | D5: 35884 | E5: KRW | F5: =IF($D5="","",$D5*IF($E5="UZS",Pricing!$B$7,IF($E5="USD",Pricing!$B$5,1))) | G5: =IF($A5="","",TEXT($A5,"yyyy-mm"))
A6: 46231 | B6: AI tools | D6: 35838 | E6: KRW | F6: =IF($D6="","",$D6*IF($E6="UZS",Pricing!$B$7,IF($E6="USD",Pricing!$B$5,1))) | G6: =IF($A6="","",TEXT($A6,"yyyy-mm"))
F7: =IF($D7="","",$D7*IF($E7="UZS",Pricing!$B$7,IF($E7="USD",Pricing!$B$5,1))) | G7: =IF($A7="","",TEXT($A7,"yyyy-mm"))
F8: =IF($D8="","",$D8*IF($E8="UZS",Pricing!$B$7,IF($E8="USD",Pricing!$B$5,1))) | G8: =IF($A8="","",TEXT($A8,"yyyy-mm"))
F9: =IF($D9="","",$D9*IF($E9="UZS",Pricing!$B$7,IF($E9="USD",Pricing!$B$5,1))) | G9: =IF($A9="","",TEXT($A9,"yyyy-mm"))
F10: =IF($D10="","",$D10*IF($E10="UZS",Pricing!$B$7,IF($E10="USD",Pricing!$B$5,1))) | G10: =IF($A10="","",TEXT($A10,"yyyy-mm"))
F11: =IF($D11="","",$D11*IF($E11="UZS",Pricing!$B$7,IF($E11="USD",Pricing!$B$5,1))) | G11: =IF($A11="","",TEXT($A11,"yyyy-mm"))
F12: =IF($D12="","",$D12*IF($E12="UZS",Pricing!$B$7,IF($E12="USD",Pricing!$B$5,1))) | G12: =IF($A12="","",TEXT($A12,"yyyy-mm"))
F13: =IF($D13="","",$D13*IF($E13="UZS",Pricing!$B$7,IF($E13="USD",Pricing!$B$5,1))) | G13: =IF($A13="","",TEXT($A13,"yyyy-mm"))
F14: =IF($D14="","",$D14*IF($E14="UZS",Pricing!$B$7,IF($E14="USD",Pricing!$B$5,1))) | G14: =IF($A14="","",TEXT($A14,"yyyy-mm"))
F15: =IF($D15="","",$D15*IF($E15="UZS",Pricing!$B$7,IF($E15="USD",Pricing!$B$5,1))) | G15: =IF($A15="","",TEXT($A15,"yyyy-mm"))
F16: =IF($D16="","",$D16*IF($E16="UZS",Pricing!$B$7,IF($E16="USD",Pricing!$B$5,1))) | G16: =IF($A16="","",TEXT($A16,"yyyy-mm"))
F17: =IF($D17="","",$D17*IF($E17="UZS",Pricing!$B$7,IF($E17="USD",Pricing!$B$5,1))) | G17: =IF($A17="","",TEXT($A17,"yyyy-mm"))
F18: =IF($D18="","",$D18*IF($E18="UZS",Pricing!$B$7,IF($E18="USD",Pricing!$B$5,1))) | G18: =IF($A18="","",TEXT($A18,"yyyy-mm"))
... F44: =IF($D44="","",$D44*IF($E44="UZS",Pricing!$B$7,IF($E44="USD",Pricing!$B$5,1))) | G44: =IF($A44="","",TEXT($A44,"yyyy-mm"))

Sheet Summary
A1: Summary
A2: Everything here is calculated from the other tabs.
A4: Money and stock | B4: KRW | C4: USD
A5: Paid to factory (all batches) | B5: =SUM(Production!$C:$C) | C5: =B5/Pricing!$B$5
A6: Freight paid (all lots) | B6: =SUM(Lots!$K$5:$K$24)*Pricing!$B$5 | C6: =B6/Pricing!$B$5
A7: Customs and other import costs | B7: =SUM(Lots!$L$5:$L$24) | C7: =B7/Pricing!$B$5
A8: Revenue before VAT (all sales) | B8: =SUM(Sales!$K$5:$K$44) | C8: =B8/Pricing!$B$5
A9: Profit from sales | B9: =SUM(Sales!$M$5:$M$44) | C9: =B9/Pricing!$B$5
A10: Running expenses | B10: =SUM(Expenses!$F$5:$F$44) | C10: =B10/Pricing!$B$5
A11: Net profit so far | B11: =B9-B10 | C11: =B11/Pricing!$B$5
A12: Value of unsold stock (at landed cost) | B12: =SUMPRODUCT(N(+Lots!$R$5:$R$24),N(+Lots!$P$5:$P$24)) | C12: =B12/Pricing!$B$5
A14: Units left | B14: Units
A15: In Korea | B15: =SUMIFS(Lots!$R$5:$R$24,Lots!$D$5:$D$24,"Korea")
A16: In Uzbekistan | B16: =SUMIFS(Lots!$R$5:$R$24,Lots!$D$5:$D$24,"Uzbekistan")
A17: Total | B17: =B15+B16
A19: Profit by month (KRW) | B19: 2026-07 | C19: 2026-08 | D19: 2026-09 | E19: 2026-10 | F19: 2026-11 | G19: 2026-12 | H19: 2027-01 | I19: 2027-02 | J19: 2027-03 | K19: 2027-04 | L19: 2027-05 | M19: 2027-06 | N19: Total
A20: Revenue before VAT | B20: =SUMIFS(Sales!$K:$K,Sales!$O:$O,B$19) | C20: =SUMIFS(Sales!$K:$K,Sales!$O:$O,C$19) | D20: =SUMIFS(Sales!$K:$K,Sales!$O:$O,D$19) | E20: =SUMIFS(Sales!$K:$K,Sales!$O:$O,E$19) | F20: =SUMIFS(Sales!$K:$K,Sales!$O:$O,F$19) | G20: =SUMIFS(Sales!$K:$K,Sales!$O:$O,G$19) | H20: =SUMIFS(Sales!$K:$K,Sales!$O:$O,H$19) | I20: =SUMIFS(Sales!$K:$K,Sales!$O:$O,I$19) | ... M20: =SUMIFS(Sales!$K:$K,Sales!$O:$O,M$19) | N20: =SUM(B20:M20)
A21: Profit from sales | B21: =SUMIFS(Sales!$M:$M,Sales!$O:$O,B$19) | C21: =SUMIFS(Sales!$M:$M,Sales!$O:$O,C$19) | D21: =SUMIFS(Sales!$M:$M,Sales!$O:$O,D$19) | E21: =SUMIFS(Sales!$M:$M,Sales!$O:$O,E$19) | F21: =SUMIFS(Sales!$M:$M,Sales!$O:$O,F$19) | G21: =SUMIFS(Sales!$M:$M,Sales!$O:$O,G$19) | H21: =SUMIFS(Sales!$M:$M,Sales!$O:$O,H$19) | I21: =SUMIFS(Sales!$M:$M,Sales!$O:$O,I$19) | ... M21: =SUMIFS(Sales!$M:$M,Sales!$O:$O,M$19) | N21: =SUM(B21:M21)
A22: Running expenses | B22: =SUMIFS(Expenses!$F:$F,Expenses!$G:$G,B$19) | C22: =SUMIFS(Expenses!$F:$F,Expenses!$G:$G,C$19) | D22: =SUMIFS(Expenses!$F:$F,Expenses!$G:$G,D$19) | E22: =SUMIFS(Expenses!$F:$F,Expenses!$G:$G,E$19) | F22: =SUMIFS(Expenses!$F:$F,Expenses!$G:$G,F$19) | G22: =SUMIFS(Expenses!$F:$F,Expenses!$G:$G,G$19) | H22: =SUMIFS(Expenses!$F:$F,Expenses!$G:$G,H$19) | I22: =SUMIFS(Expenses!$F:$F,Expenses!$G:$G,I$19) | ... M22: =SUMIFS(Expenses!$F:$F,Expenses!$G:$G,M$19) | N22: =SUM(B22:M22)
A23: Net profit | B23: =B21-B22 | C23: =C21-C22 | D23: =D21-D22 | E23: =E21-E22 | F23: =F21-F22 | G23: =G21-G22 | H23: =H21-H22 | I23: =I21-I22 | ... M23: =M21-M22 | N23: =SUM(B23:M23)
